<?xml version="1.0" encoding="UTF-8"?>
<root>
  <instruction text="move to the box before going to the table"/>
  <world>
    <object name="R" type="robot" />
    <object name="C" type="chair" />
    <object name="T" type="table" />
    <object name="B" type="box" />
  </world>

  <VP>
    <grounding>
      <grounding_set>
        <constraint type="inside">
	  <parent>
	    <region type="na">
	      <object name="R" type="robot"/>
	    </region>
	  </parent>
	  <child>
	    <region type="na">
	      <object name="B" type="box"/>
	    </region>
	  </child>
	</constraint>
        <func_kernel type="1" weight="0.2">
	  <object name="T" type="table"/>
        </func_kernel>
      </grounding_set>
    </grounding>
    <VB text="move"/>
    <PP>
      <grounding>
        <grounding_set>
          <region type="na">
            <object name="B" type="box"/>
          </region>
        </grounding_set>
      </grounding>
      <TO text="to"/>
      <NP>
        <grounding>
          <grounding_set>
            <region type="na">
              <object name="B" type="box"/>
            </region>
          </grounding_set>
        </grounding>
        <DT text="the"/>
	<NN text="box"/>
      </NP>
    </PP>
    <PP>
      <grounding>
        <grounding_set>
          <func_kernel type="1" weight="0.2">
	    <object name="T" type="table"/>
          </func_kernel>
        </grounding_set>
      </grounding>
      <IN text="before"/>
      <VP>
        <grounding>
          <grounding_set>
            <func_kernel type="1" weight="0.2">
	      <object name="T" type="table"/>
            </func_kernel>
          </grounding_set>
        </grounding>
        <VBG text="going"/>
        <PP>
          <grounding>
            <grounding_set>
              <func_kernel type="1" weight="0.2">
	      	<object name="T" type="table"/>
              </func_kernel>
            </grounding_set>
          </grounding>
          <TO text="to"/>
          <NP>
            <grounding>
              <grounding_set>
	        <object name="T" type="table"/>
              </grounding_set>
            </grounding>
            <DT text="the"/>
            <NN text="table"/>
          </NP>
        </PP>
      </VP>
    </PP>
  </VP>
</root>
